<?xml version="1.0" encoding="UTF-8"?><record_update>
    <sys_ui_list action="DELETE" parent="" relationship="" sys_domain="global" table="x_962293_gconfig_zen_groups" version="2" view="">
        <sys_ui_list_element action="INSERT_OR_UPDATE">
            <average_value>false</average_value>
            <element>sys_import_row</element>
            <list_id display_value="x_962293_gconfig_zen_groups" element="NULL" name="x_962293_gconfig_zen_groups" parent="NULL" relationship="NULL" sys_domain="global" view="Default view">845b55bf47b03110789e057d826d4327</list_id>
            <max_value>false</max_value>
            <min_value>false</min_value>
            <position>0</position>
            <sum>false</sum>
            <sys_created_by>admin</sys_created_by>
            <sys_created_on>2023-08-28 13:19:48</sys_created_on>
            <sys_id>0c5b55bf47b03110789e057d826d4328</sys_id>
            <sys_mod_count>0</sys_mod_count>
            <sys_updated_by>admin</sys_updated_by>
            <sys_updated_on>2023-08-28 13:19:48</sys_updated_on>
        </sys_ui_list_element>
        <sys_ui_list_element action="INSERT_OR_UPDATE">
            <average_value>false</average_value>
            <element>sys_import_set</element>
            <list_id display_value="x_962293_gconfig_zen_groups" element="NULL" name="x_962293_gconfig_zen_groups" parent="NULL" relationship="NULL" sys_domain="global" view="Default view">845b55bf47b03110789e057d826d4327</list_id>
            <max_value>false</max_value>
            <min_value>false</min_value>
            <position>1</position>
            <sum>false</sum>
            <sys_created_by>admin</sys_created_by>
            <sys_created_on>2023-08-28 13:19:48</sys_created_on>
            <sys_id>c05b55bf47b03110789e057d826d4329</sys_id>
            <sys_mod_count>0</sys_mod_count>
            <sys_updated_by>admin</sys_updated_by>
            <sys_updated_on>2023-08-28 13:19:48</sys_updated_on>
        </sys_ui_list_element>
        <sys_ui_list_element action="INSERT_OR_UPDATE">
            <average_value>false</average_value>
            <element>sys_import_state</element>
            <list_id display_value="x_962293_gconfig_zen_groups" element="NULL" name="x_962293_gconfig_zen_groups" parent="NULL" relationship="NULL" sys_domain="global" view="Default view">845b55bf47b03110789e057d826d4327</list_id>
            <max_value>false</max_value>
            <min_value>false</min_value>
            <position>2</position>
            <sum>false</sum>
            <sys_created_by>admin</sys_created_by>
            <sys_created_on>2023-08-28 13:19:48</sys_created_on>
            <sys_id>445b55bf47b03110789e057d826d4329</sys_id>
            <sys_mod_count>0</sys_mod_count>
            <sys_updated_by>admin</sys_updated_by>
            <sys_updated_on>2023-08-28 13:19:48</sys_updated_on>
        </sys_ui_list_element>
        <sys_ui_list_element action="INSERT_OR_UPDATE">
            <average_value>false</average_value>
            <element>sys_target_table</element>
            <list_id display_value="x_962293_gconfig_zen_groups" element="NULL" name="x_962293_gconfig_zen_groups" parent="NULL" relationship="NULL" sys_domain="global" view="Default view">845b55bf47b03110789e057d826d4327</list_id>
            <max_value>false</max_value>
            <min_value>false</min_value>
            <position>3</position>
            <sum>false</sum>
            <sys_created_by>admin</sys_created_by>
            <sys_created_on>2023-08-28 13:19:48</sys_created_on>
            <sys_id>c45b55bf47b03110789e057d826d4329</sys_id>
            <sys_mod_count>0</sys_mod_count>
            <sys_updated_by>admin</sys_updated_by>
            <sys_updated_on>2023-08-28 13:19:48</sys_updated_on>
        </sys_ui_list_element>
        <sys_ui_list_element action="INSERT_OR_UPDATE">
            <average_value>false</average_value>
            <element>sys_target_sys_id</element>
            <list_id display_value="x_962293_gconfig_zen_groups" element="NULL" name="x_962293_gconfig_zen_groups" parent="NULL" relationship="NULL" sys_domain="global" view="Default view">845b55bf47b03110789e057d826d4327</list_id>
            <max_value>false</max_value>
            <min_value>false</min_value>
            <position>4</position>
            <sum>false</sum>
            <sys_created_by>admin</sys_created_by>
            <sys_created_on>2023-08-28 13:19:48</sys_created_on>
            <sys_id>485b55bf47b03110789e057d826d4329</sys_id>
            <sys_mod_count>0</sys_mod_count>
            <sys_updated_by>admin</sys_updated_by>
            <sys_updated_on>2023-08-28 13:19:48</sys_updated_on>
        </sys_ui_list_element>
        <sys_ui_list_element action="INSERT_OR_UPDATE">
            <average_value>false</average_value>
            <element>sys_row_error</element>
            <list_id display_value="x_962293_gconfig_zen_groups" element="NULL" name="x_962293_gconfig_zen_groups" parent="NULL" relationship="NULL" sys_domain="global" view="Default view">845b55bf47b03110789e057d826d4327</list_id>
            <max_value>false</max_value>
            <min_value>false</min_value>
            <position>5</position>
            <sum>false</sum>
            <sys_created_by>admin</sys_created_by>
            <sys_created_on>2023-08-28 13:19:48</sys_created_on>
            <sys_id>c85b55bf47b03110789e057d826d4329</sys_id>
            <sys_mod_count>0</sys_mod_count>
            <sys_updated_by>admin</sys_updated_by>
            <sys_updated_on>2023-08-28 13:19:48</sys_updated_on>
        </sys_ui_list_element>
        <sys_ui_list action="INSERT_OR_UPDATE">
            <average_value>false</average_value>
            <element/>
            <max_value>false</max_value>
            <min_value>false</min_value>
            <name>x_962293_gconfig_zen_groups</name>
            <parent/>
            <position/>
            <relationship/>
            <sum>false</sum>
            <sys_class_name>sys_ui_list</sys_class_name>
            <sys_created_by>admin</sys_created_by>
            <sys_created_on>2023-08-28 13:19:48</sys_created_on>
            <sys_domain>global</sys_domain>
            <sys_domain_path>/</sys_domain_path>
            <sys_id>845b55bf47b03110789e057d826d4327</sys_id>
            <sys_mod_count>0</sys_mod_count>
            <sys_name>x_962293_gconfig_zen_groups</sys_name>
            <sys_package display_value="GConfig" source="x_962293_gconfig">4afb42b147232110789e057d826d432e</sys_package>
            <sys_policy/>
            <sys_scope display_value="GConfig">4afb42b147232110789e057d826d432e</sys_scope>
            <sys_update_name>sys_ui_list_x_962293_gconfig_zen_groups_null</sys_update_name>
            <sys_updated_by>admin</sys_updated_by>
            <sys_updated_on>2023-08-28 13:19:48</sys_updated_on>
            <sys_user/>
            <view display_value="Default view" name="NULL">Default view</view>
            <view_name/>
        </sys_ui_list>
    </sys_ui_list>
    <sys_update_version action="INSERT_OR_UPDATE">
        <action>DELETE</action>
        <application display_value="GConfig">4afb42b147232110789e057d826d432e</application>
        <file_path/>
        <instance_id>1dca40e8db5732c04c1ff70fbf961996</instance_id>
        <instance_name>dev38306</instance_name>
        <name>sys_ui_list_x_962293_gconfig_zen_groups_null</name>
        <payload><![CDATA[<?xml version="1.0" encoding="UTF-8"?><record_update><sys_ui_list parent="" relationship="" sys_domain="global" table="x_962293_gconfig_zen_groups" version="2" view=""><sys_ui_list_element action="INSERT_OR_UPDATE"><average_value>false</average_value><element>sys_import_row</element><list_id display_value="x_962293_gconfig_zen_groups" element="NULL" name="x_962293_gconfig_zen_groups" parent="NULL" relationship="NULL" sys_domain="global" view="Default view">845b55bf47b03110789e057d826d4327</list_id><max_value>false</max_value><min_value>false</min_value><position>0</position><sum>false</sum><sys_created_by>admin</sys_created_by><sys_created_on>2023-08-28 13:19:48</sys_created_on><sys_id>0c5b55bf47b03110789e057d826d4328</sys_id><sys_mod_count>0</sys_mod_count><sys_updated_by>admin</sys_updated_by><sys_updated_on>2023-08-28 13:19:48</sys_updated_on></sys_ui_list_element><sys_ui_list_element action="INSERT_OR_UPDATE"><average_value>false</average_value><element>sys_import_set</element><list_id display_value="x_962293_gconfig_zen_groups" element="NULL" name="x_962293_gconfig_zen_groups" parent="NULL" relationship="NULL" sys_domain="global" view="Default view">845b55bf47b03110789e057d826d4327</list_id><max_value>false</max_value><min_value>false</min_value><position>1</position><sum>false</sum><sys_created_by>admin</sys_created_by><sys_created_on>2023-08-28 13:19:48</sys_created_on><sys_id>c05b55bf47b03110789e057d826d4329</sys_id><sys_mod_count>0</sys_mod_count><sys_updated_by>admin</sys_updated_by><sys_updated_on>2023-08-28 13:19:48</sys_updated_on></sys_ui_list_element><sys_ui_list_element action="INSERT_OR_UPDATE"><average_value>false</average_value><element>sys_import_state</element><list_id display_value="x_962293_gconfig_zen_groups" element="NULL" name="x_962293_gconfig_zen_groups" parent="NULL" relationship="NULL" sys_domain="global" view="Default view">845b55bf47b03110789e057d826d4327</list_id><max_value>false</max_value><min_value>false</min_value><position>2</position><sum>false</sum><sys_created_by>admin</sys_created_by><sys_created_on>2023-08-28 13:19:48</sys_created_on><sys_id>445b55bf47b03110789e057d826d4329</sys_id><sys_mod_count>0</sys_mod_count><sys_updated_by>admin</sys_updated_by><sys_updated_on>2023-08-28 13:19:48</sys_updated_on></sys_ui_list_element><sys_ui_list_element action="INSERT_OR_UPDATE"><average_value>false</average_value><element>sys_target_table</element><list_id display_value="x_962293_gconfig_zen_groups" element="NULL" name="x_962293_gconfig_zen_groups" parent="NULL" relationship="NULL" sys_domain="global" view="Default view">845b55bf47b03110789e057d826d4327</list_id><max_value>false</max_value><min_value>false</min_value><position>3</position><sum>false</sum><sys_created_by>admin</sys_created_by><sys_created_on>2023-08-28 13:19:48</sys_created_on><sys_id>c45b55bf47b03110789e057d826d4329</sys_id><sys_mod_count>0</sys_mod_count><sys_updated_by>admin</sys_updated_by><sys_updated_on>2023-08-28 13:19:48</sys_updated_on></sys_ui_list_element><sys_ui_list_element action="INSERT_OR_UPDATE"><average_value>false</average_value><element>sys_target_sys_id</element><list_id display_value="x_962293_gconfig_zen_groups" element="NULL" name="x_962293_gconfig_zen_groups" parent="NULL" relationship="NULL" sys_domain="global" view="Default view">845b55bf47b03110789e057d826d4327</list_id><max_value>false</max_value><min_value>false</min_value><position>4</position><sum>false</sum><sys_created_by>admin</sys_created_by><sys_created_on>2023-08-28 13:19:48</sys_created_on><sys_id>485b55bf47b03110789e057d826d4329</sys_id><sys_mod_count>0</sys_mod_count><sys_updated_by>admin</sys_updated_by><sys_updated_on>2023-08-28 13:19:48</sys_updated_on></sys_ui_list_element><sys_ui_list_element action="INSERT_OR_UPDATE"><average_value>false</average_value><element>sys_row_error</element><list_id display_value="x_962293_gconfig_zen_groups" element="NULL" name="x_962293_gconfig_zen_groups" parent="NULL" relationship="NULL" sys_domain="global" view="Default view">845b55bf47b03110789e057d826d4327</list_id><max_value>false</max_value><min_value>false</min_value><position>5</position><sum>false</sum><sys_created_by>admin</sys_created_by><sys_created_on>2023-08-28 13:19:48</sys_created_on><sys_id>c85b55bf47b03110789e057d826d4329</sys_id><sys_mod_count>0</sys_mod_count><sys_updated_by>admin</sys_updated_by><sys_updated_on>2023-08-28 13:19:48</sys_updated_on></sys_ui_list_element><sys_ui_list action="INSERT_OR_UPDATE"><average_value>false</average_value><element/><max_value>false</max_value><min_value>false</min_value><name>x_962293_gconfig_zen_groups</name><parent/><position/><relationship/><sum>false</sum><sys_class_name>sys_ui_list</sys_class_name><sys_created_by>admin</sys_created_by><sys_created_on>2023-08-28 13:19:48</sys_created_on><sys_domain>global</sys_domain><sys_domain_path>/</sys_domain_path><sys_id>845b55bf47b03110789e057d826d4327</sys_id><sys_mod_count>0</sys_mod_count><sys_name>x_962293_gconfig_zen_groups</sys_name><sys_package display_value="GConfig" source="x_962293_gconfig">4afb42b147232110789e057d826d432e</sys_package><sys_policy/><sys_scope display_value="GConfig">4afb42b147232110789e057d826d432e</sys_scope><sys_update_name>sys_ui_list_x_962293_gconfig_zen_groups_null</sys_update_name><sys_updated_by>admin</sys_updated_by><sys_updated_on>2023-08-28 13:19:48</sys_updated_on><sys_user/><view display_value="Default view" name="NULL">Default view</view><view_name/></sys_ui_list></sys_ui_list></record_update>]]></payload>
        <payload_hash>344755146</payload_hash>
        <record_name>Zgroups</record_name>
        <reverted_from/>
        <source>7f9d8e8b47b72110789e057d826d4309</source>
        <source_table>sys_update_set</source_table>
        <state>previous</state>
        <sys_created_by>admin</sys_created_by>
        <sys_created_on>2023-08-28 15:26:29</sys_created_on>
        <sys_id>4058397b47343110789e057d826d436b</sys_id>
        <sys_mod_count>0</sys_mod_count>
        <sys_recorded_at>18a3cc0e7200000001</sys_recorded_at>
        <sys_updated_by>admin</sys_updated_by>
        <sys_updated_on>2023-08-28 15:26:29</sys_updated_on>
        <type>List Layout</type>
        <update_guid>0058397bc7343110805005c6eb58486b</update_guid>
        <update_guid_history>0058397bc7343110805005c6eb58486b:344755146</update_guid_history>
    </sys_update_version>
    <sys_metadata_delete action="INSERT_OR_UPDATE">
        <sys_audit_delete/>
        <sys_class_name>sys_metadata_delete</sys_class_name>
        <sys_created_by>admin</sys_created_by>
        <sys_created_on>2023-08-28 15:26:29</sys_created_on>
        <sys_db_object display_value="" name="sys_ui_list">sys_ui_list</sys_db_object>
        <sys_id>4bdd407856a844329813be87f09275f9</sys_id>
        <sys_metadata>845b55bf47b03110789e057d826d4327</sys_metadata>
        <sys_mod_count>0</sys_mod_count>
        <sys_name>x_962293_gconfig_zen_groups</sys_name>
        <sys_package display_value="GConfig" source="x_962293_gconfig">4afb42b147232110789e057d826d432e</sys_package>
        <sys_parent display_value="">fb4b15bf47b03110789e057d826d43a4</sys_parent>
        <sys_policy/>
        <sys_scope display_value="GConfig">4afb42b147232110789e057d826d432e</sys_scope>
        <sys_scope_delete display_value="">0ebef6f1134a49f68249a7d3c1e5b564</sys_scope_delete>
        <sys_update_name>sys_ui_list_x_962293_gconfig_zen_groups_null</sys_update_name>
        <sys_update_version display_value="sys_ui_list_x_962293_gconfig_zen_groups_null">4058397b47343110789e057d826d436b</sys_update_version>
        <sys_updated_by>admin</sys_updated_by>
        <sys_updated_on>2023-08-28 15:26:29</sys_updated_on>
    </sys_metadata_delete>
</record_update>
